README.md
setup.py
vivarium_multibody/__init__.py
vivarium_multibody.egg-info/PKG-INFO
vivarium_multibody.egg-info/SOURCES.txt
vivarium_multibody.egg-info/dependency_links.txt
vivarium_multibody.egg-info/entry_points.txt
vivarium_multibody.egg-info/requires.txt
vivarium_multibody.egg-info/top_level.txt
vivarium_multibody/composites/__init__.py
vivarium_multibody/composites/grow_divide.py
vivarium_multibody/composites/lattice.py
vivarium_multibody/composites/static_lattice.py
vivarium_multibody/library/__init__.py
vivarium_multibody/library/lattice_utils.py
vivarium_multibody/library/pymunk_multibody.py
vivarium_multibody/plots/__init__.py
vivarium_multibody/plots/snapshots.py
vivarium_multibody/plots/snapshots_video.py
vivarium_multibody/plots/trajectory.py
vivarium_multibody/processes/__init__.py
vivarium_multibody/processes/derive_globals.py
vivarium_multibody/processes/diffusion_field.py
vivarium_multibody/processes/exchange.py
vivarium_multibody/processes/local_field.py
vivarium_multibody/processes/multibody_physics.py
vivarium_multibody/processes/static_field.py