Metadata-Version: 2.1
Name: vivarium-multibody
Version: 0.0.14
Summary: UNKNOWN
Home-page: https://github.com/vivarium-collective/vivarium-pymunk
Author: Eran Agmon
Author-email: eagmon@stanford.edu
License: MIT
Platform: UNKNOWN
